{
    "IsActive": true,
    "IsOmniScriptEmbeddable": false,
    "Name": "DRGetCaseRecordTypeId",
    "OmniProcessId": {
        "Name": "sfiEnergyConsoleFSEmailAndCaseCreation",
        "VlocityDataPackType": "VlocityMatchingKeyObject",
        "VlocityMatchingRecordSourceKey": "OmniProcess/sfiEnergyConsole/FSEmailAndCaseCreation/Procedure",
        "VlocityRecordSObjectType": "OmniProcess"
    },
    "PropertySetConfig": {
        "actionMessage": "",
        "additionalInput": {
            "recordTypeName": "Service",
            "sObjectName": "Case"
        },
        "additionalOutput": {
        },
        "bundle": "sfiEnergyConsoleFSGetRecordTypeId",
        "chainOnStep": false,
        "dataRaptor Input Parameters": [
        ],
        "disOnTplt": false,
        "executionConditionalFormula": "%isRescheduleFlow% == false",
        "failOnStepError": true,
        "failureConditionalFormula": "",
        "failureResponse": {
            "ErrorMessage": "DRGetCaseRecordTypeId : Failed to retrieve case recordtype id"
        },
        "ignoreCache": false,
        "label": "DataRaptorExtractAction1",
        "responseJSONNode": "",
        "responseJSONPath": "",
        "returnOnlyAdditionalOutput": false,
        "returnOnlyFailureResponse": false,
        "sendJSONNode": "",
        "sendJSONPath": "",
        "sendOnlyAdditionalInput": true,
        "show": null,
        "useFormulas": true
    },
    "Type": "DataRaptor Extract Action",
    "VlocityDataPackType": "SObject",
    "VlocityRecordSObjectType": "OmniProcessElement",
    "VlocityRecordSourceKey": "OmniProcessElement/OmniProcess/sfiEnergyConsole/FSEmailAndCaseCreation/Procedure/DRGetCaseRecordTypeId"
}