{
    "IsActive": true,
    "IsOmniScriptEmbeddable": false,
    "Name": "commentsReview",
    "OmniProcessId": {
        "Name": "sfiEnergyConsoleFSScheduleAppointment",
        "VlocityDataPackType": "VlocityMatchingKeyObject",
        "VlocityMatchingRecordSourceKey": "OmniProcess/sfiEnergyConsole/FSScheduleAppointment/Multi-Language",
        "VlocityRecordSObjectType": "OmniProcess"
    },
    "ParentElementId": {
        "Name": "serviceDescriptionReview",
        "OmniProcessId": {
            "Name": "sfiEnergyConsoleFSScheduleAppointment",
            "VlocityDataPackType": "VlocityMatchingKeyObject",
            "VlocityMatchingRecordSourceKey": "OmniProcess/sfiEnergyConsole/FSScheduleAppointment/Multi-Language",
            "VlocityRecordSObjectType": "OmniProcess"
        },
        "VlocityDataPackType": "VlocityMatchingKeyObject",
        "VlocityMatchingRecordSourceKey": "OmniProcessElement/OmniProcess/sfiEnergyConsole/FSScheduleAppointment/Multi-Language/serviceDescriptionReview",
        "VlocityRecordSObjectType": "OmniProcessElement"
    },
    "ParentElementName": "serviceDescriptionReview",
    "ParentElementType": "Block",
    "PropertySetConfig": {
        "HTMLTemplateId": "",
        "accessibleInFutureSteps": false,
        "conditionType": "Hide if False",
        "controlWidth": 12,
        "debounceValue": 0,
        "defaultValue": "%serviceDescriptionFinal%",
        "disOnTplt": false,
        "help": false,
        "helpText": "",
        "hide": false,
        "inputWidth": 12,
        "label": "",
        "maxLength": 255,
        "minLength": 0,
        "pattern": "",
        "placeholder": "",
        "ptrnErrText": "",
        "readOnly": true,
        "repeat": false,
        "repeatClone": false,
        "repeatLimit": null,
        "required": false,
        "show": null,
        "showInputWidth": false
    },
    "Type": "Text Area",
    "VlocityDataPackType": "SObject",
    "VlocityRecordSObjectType": "OmniProcessElement",
    "VlocityRecordSourceKey": "OmniProcessElement/OmniProcess/sfiEnergyConsole/FSScheduleAppointment/Multi-Language/commentsReview"
}